futurist/__init__.py
futurist/_futures.py
futurist/_green.py
futurist/_thread.py
futurist/_utils.py
futurist/periodics.py
futurist/rejection.py
futurist/waiters.py
futurist/tests/__init__.py
futurist/tests/base.py
futurist/tests/test_executors.py
futurist/tests/test_periodics.py
futurist/tests/test_waiters.py
futurist-3.2.1.dist-info/AUTHORS
futurist-3.2.1.dist-info/LICENSE
futurist-3.2.1.dist-info/METADATA
futurist-3.2.1.dist-info/WHEEL
futurist-3.2.1.dist-info/pbr.json
futurist-3.2.1.dist-info/top_level.txt
futurist-3.2.1.dist-info/RECORD
